redis_mass_get/__init__.py
redis_mass_get/__main__.py
redis_mass_get/query.py
redis_mass_get/processors/CsvProcessor.py
redis_mass_get/processors/JsonProcessor.py
redis_mass_get/processors/MemoryProcessor.py
redis_mass_get/processors/ProcessorBase.py
redis_mass_get/processors/TextProcessor.py
redis_mass_get/processors/__init__.py
redis_mass_get/processors/exceptions.py
redis_mass_get-0.0.11.dist-info/LICENSE.md
redis_mass_get-0.0.11.dist-info/METADATA
redis_mass_get-0.0.11.dist-info/WHEEL
redis_mass_get-0.0.11.dist-info/entry_points.txt
redis_mass_get-0.0.11.dist-info/top_level.txt
redis_mass_get-0.0.11.dist-info/RECORD
