Metadata-Version: 2.1
Name: redis-mass-get
Version: 0.0.11
Summary: Queries KEYS from Redis and performans an efficient MGET. Helps with querying your Redis.
Home-page: https://github.com/KeesCBakker/redis-mass-get
Author: Kees C. Bakker / KeesTalksTech
Author-email: info@keestalkstech.com
License: MIT
Platform: UNKNOWN
Classifier: License :: OSI Approved :: MIT License
Classifier: Programming Language :: Python :: 3.7
Requires-Dist: redis
